[{
  "_id": {
    "$oid": "63a2e268d6a3529c1660f590"
  },
  "paymentPurpose": "Rojkharido Grocery Store Registration",
  "planMonth": "1",
  "paymentStatus": "1",
  "paymentId": "pay_KuWw9Gi6geI2hl",
  "storeId": "63a2e268d6a3529c1660f58e",
  "type": "GROCERY",
  "amount": "999",
  "tax": "179",
  "totalAmount": "1178",
  "date": "Wed Dec 21 2022 16:09:36 GMT+0530 (India Standard Time)",
  "__v": 0
},{
  "_id": {
    "$oid": "63a2e31ad6a3529c1660f59d"
  },
  "paymentPurpose": "Rojkharido Grocery Store Registration",
  "planMonth": "1",
  "paymentStatus": "1",
  "paymentId": "pay_KuWzH6L3ZCVb8x",
  "storeId": "63a2e31ad6a3529c1660f59b",
  "type": "GROCERY",
  "amount": "999",
  "tax": "179",
  "totalAmount": "1178",
  "date": "Wed Dec 21 2022 16:12:34 GMT+0530 (India Standard Time)",
  "__v": 0
},{
  "_id": {
    "$oid": "63a2e3efd6a3529c1660f5aa"
  },
  "paymentPurpose": "Rojkharido Grocery Store Registration",
  "planMonth": "1",
  "paymentStatus": "1",
  "paymentId": "pay_KuX31FsuuAmTJF",
  "storeId": "63a2e3efd6a3529c1660f5a8",
  "type": "GROCERY",
  "amount": "999",
  "tax": "179",
  "totalAmount": "1178",
  "date": "Wed Dec 21 2022 16:16:07 GMT+0530 (India Standard Time)",
  "__v": 0
},{
  "_id": {
    "$oid": "63a2e496d6a3529c1660f5b7"
  },
  "paymentPurpose": "Rojkharido Grocery Store Registration",
  "planMonth": "1",
  "paymentStatus": "1",
  "paymentId": "pay_KuX5yFfT0T6n3j",
  "storeId": "63a2e496d6a3529c1660f5b5",
  "type": "GROCERY",
  "amount": "999",
  "tax": "179",
  "totalAmount": "1178",
  "date": "Wed Dec 21 2022 16:18:54 GMT+0530 (India Standard Time)",
  "__v": 0
},{
  "_id": {
    "$oid": "63a2e52ed6a3529c1660f5c4"
  },
  "paymentPurpose": "Rojkharido Grocery Store Registration",
  "planMonth": "1",
  "paymentStatus": "1",
  "paymentId": "pay_KuX8e7wqp4E4bR",
  "storeId": "63a2e52ed6a3529c1660f5c2",
  "type": "GROCERY",
  "amount": "999",
  "tax": "179",
  "totalAmount": "1178",
  "date": "Wed Dec 21 2022 16:21:26 GMT+0530 (India Standard Time)",
  "__v": 0
},{
  "_id": {
    "$oid": "63a2e5b0d6a3529c1660f5d1"
  },
  "paymentPurpose": "Rojkharido Grocery Store Registration",
  "planMonth": "1",
  "paymentStatus": "1",
  "paymentId": "pay_KuXAwOmzuSgmDB",
  "storeId": "63a2e5b0d6a3529c1660f5cf",
  "type": "GROCERY",
  "amount": "999",
  "tax": "179",
  "totalAmount": "1178",
  "date": "Wed Dec 21 2022 16:23:36 GMT+0530 (India Standard Time)",
  "__v": 0
},{
  "_id": {
    "$oid": "63a2e63ad6a3529c1660f5de"
  },
  "paymentPurpose": "Rojkharido Grocery Store Registration",
  "planMonth": "1",
  "paymentStatus": "1",
  "paymentId": "pay_KuXDNIkiBcSSdJ",
  "storeId": "63a2e63ad6a3529c1660f5dc",
  "type": "GROCERY",
  "amount": "999",
  "tax": "179",
  "totalAmount": "1178",
  "date": "Wed Dec 21 2022 16:25:54 GMT+0530 (India Standard Time)",
  "__v": 0
},{
  "_id": {
    "$oid": "63a2e6f0d6a3529c1660f5eb"
  },
  "paymentPurpose": "Rojkharido Grocery Store Registration",
  "planMonth": "1",
  "paymentStatus": "1",
  "paymentId": "pay_KuXGZJwcHCMUBJ",
  "storeId": "63a2e6f0d6a3529c1660f5e9",
  "type": "GROCERY",
  "amount": "999",
  "tax": "179",
  "totalAmount": "1178",
  "date": "Wed Dec 21 2022 16:28:56 GMT+0530 (India Standard Time)",
  "__v": 0
},{
  "_id": {
    "$oid": "63a2e774d6a3529c1660f5f8"
  },
  "paymentPurpose": "Rojkharido Grocery Store Registration",
  "planMonth": "1",
  "paymentStatus": "1",
  "paymentId": "pay_KuXItnhyemfpK1",
  "storeId": "63a2e774d6a3529c1660f5f6",
  "type": "GROCERY",
  "amount": "999",
  "tax": "179",
  "totalAmount": "1178",
  "date": "Wed Dec 21 2022 16:31:08 GMT+0530 (India Standard Time)",
  "__v": 0
},{
  "_id": {
    "$oid": "63a2e9c9d6a3529c1660f605"
  },
  "paymentPurpose": "Rojkharido Grocery Store Registration",
  "planMonth": "1",
  "paymentStatus": "1",
  "paymentId": "pay_KuXTQTHfSR4eRf",
  "storeId": "63a2e9c9d6a3529c1660f603",
  "type": "GROCERY",
  "amount": "999",
  "tax": "179",
  "totalAmount": "1178",
  "date": "Wed Dec 21 2022 16:41:05 GMT+0530 (India Standard Time)",
  "__v": 0
},{
  "_id": {
    "$oid": "63a2ea59d6a3529c1660f612"
  },
  "paymentPurpose": "Rojkharido Grocery Store Registration",
  "planMonth": "1",
  "paymentStatus": "1",
  "paymentId": "pay_KuXVwx6zhxGPOQ",
  "storeId": "63a2ea59d6a3529c1660f610",
  "type": "GROCERY",
  "amount": "999",
  "tax": "179",
  "totalAmount": "1178",
  "date": "Wed Dec 21 2022 16:43:29 GMT+0530 (India Standard Time)",
  "__v": 0
},{
  "_id": {
    "$oid": "63a2eacdd6a3529c1660f61f"
  },
  "paymentPurpose": "Rojkharido Grocery Store Registration",
  "planMonth": "1",
  "paymentStatus": "1",
  "paymentId": "pay_KuXXzWj4txtrrx",
  "storeId": "63a2eacdd6a3529c1660f61d",
  "type": "GROCERY",
  "amount": "999",
  "tax": "179",
  "totalAmount": "1178",
  "date": "Wed Dec 21 2022 16:45:25 GMT+0530 (India Standard Time)",
  "__v": 0
},{
  "_id": {
    "$oid": "63a2ebc0d6a3529c1660f62c"
  },
  "paymentPurpose": "Rojkharido Grocery Store Registration",
  "planMonth": "1",
  "paymentStatus": "1",
  "paymentId": "pay_KuXcHEm9j30bA7",
  "storeId": "63a2ebc0d6a3529c1660f62a",
  "type": "GROCERY",
  "amount": "999",
  "tax": "179",
  "totalAmount": "1178",
  "date": "Wed Dec 21 2022 16:49:28 GMT+0530 (India Standard Time)",
  "__v": 0
},{
  "_id": {
    "$oid": "63a2ec52d6a3529c1660f639"
  },
  "paymentPurpose": "Rojkharido Grocery Store Registration",
  "planMonth": "1",
  "paymentStatus": "1",
  "paymentId": "pay_KuXeqH44D8gAXw",
  "storeId": "63a2ec52d6a3529c1660f637",
  "type": "GROCERY",
  "amount": "999",
  "tax": "179",
  "totalAmount": "1178",
  "date": "Wed Dec 21 2022 16:51:54 GMT+0530 (India Standard Time)",
  "__v": 0
},{
  "_id": {
    "$oid": "63a2ed49d6a3529c1660f646"
  },
  "paymentPurpose": "Rojkharido Grocery Store Registration",
  "planMonth": "1",
  "paymentStatus": "1",
  "paymentId": "pay_KuXjCGA6EyzkVb",
  "storeId": "63a2ed49d6a3529c1660f644",
  "type": "GROCERY",
  "amount": "999",
  "tax": "179",
  "totalAmount": "1178",
  "date": "Wed Dec 21 2022 16:56:01 GMT+0530 (India Standard Time)",
  "__v": 0
},{
  "_id": {
    "$oid": "63a2edc1d6a3529c1660f653"
  },
  "paymentPurpose": "Rojkharido Grocery Store Registration",
  "planMonth": "1",
  "paymentStatus": "1",
  "paymentId": "pay_KuXlI9puLqFKv2",
  "storeId": "63a2edc1d6a3529c1660f651",
  "type": "GROCERY",
  "amount": "999",
  "tax": "179",
  "totalAmount": "1178",
  "date": "Wed Dec 21 2022 16:58:01 GMT+0530 (India Standard Time)",
  "__v": 0
},{
  "_id": {
    "$oid": "63a2ee78d6a3529c1660f660"
  },
  "paymentPurpose": "Rojkharido Grocery Store Registration",
  "planMonth": "1",
  "paymentStatus": "1",
  "paymentId": "pay_KuXoWykLE8PfDn",
  "storeId": "63a2ee78d6a3529c1660f65e",
  "type": "GROCERY",
  "amount": "999",
  "tax": "179",
  "totalAmount": "1178",
  "date": "Wed Dec 21 2022 17:01:04 GMT+0530 (India Standard Time)",
  "__v": 0
},{
  "_id": {
    "$oid": "63a2ef1cd6a3529c1660f66d"
  },
  "paymentPurpose": "Rojkharido Grocery Store Registration",
  "planMonth": "1",
  "paymentStatus": "1",
  "paymentId": "pay_KuXrDSyJPvaBhP",
  "storeId": "63a2ef1cd6a3529c1660f66b",
  "type": "GROCERY",
  "amount": "999",
  "tax": "179",
  "totalAmount": "1178",
  "date": "Wed Dec 21 2022 17:03:48 GMT+0530 (India Standard Time)",
  "__v": 0
},{
  "_id": {
    "$oid": "63a2efefd6a3529c1660f67a"
  },
  "paymentPurpose": "Rojkharido Grocery Store Registration",
  "planMonth": "1",
  "paymentStatus": "1",
  "paymentId": "pay_KuXv8IUYjRBiks",
  "storeId": "63a2efefd6a3529c1660f678",
  "type": "GROCERY",
  "amount": "999",
  "tax": "179",
  "totalAmount": "1178",
  "date": "Wed Dec 21 2022 17:07:19 GMT+0530 (India Standard Time)",
  "__v": 0
},{
  "_id": {
    "$oid": "63a2f0aad6a3529c1660f687"
  },
  "paymentPurpose": "Rojkharido Grocery Store Registration",
  "planMonth": "1",
  "paymentStatus": "1",
  "paymentId": "pay_KuXyQXsywi3ODX",
  "storeId": "63a2f0aad6a3529c1660f685",
  "type": "GROCERY",
  "amount": "999",
  "tax": "179",
  "totalAmount": "1178",
  "date": "Wed Dec 21 2022 17:10:26 GMT+0530 (India Standard Time)",
  "__v": 0
},{
  "_id": {
    "$oid": "63a2f154d6a3529c1660f694"
  },
  "paymentPurpose": "Rojkharido Grocery Store Registration",
  "planMonth": "1",
  "paymentStatus": "1",
  "paymentId": "pay_KuY1QOhEJQHtKN",
  "storeId": "63a2f154d6a3529c1660f692",
  "type": "GROCERY",
  "amount": "999",
  "tax": "179",
  "totalAmount": "1178",
  "date": "Wed Dec 21 2022 17:13:16 GMT+0530 (India Standard Time)",
  "__v": 0
},{
  "_id": {
    "$oid": "63a2fd16d7b6cc7df588b006"
  },
  "paymentPurpose": "Rojkharido Restaurant Registration",
  "planMonth": "1",
  "paymentStatus": "1",
  "paymentId": "pay_KuYsP9GCm7KeU9",
  "storeId": "63a2fd16d7b6cc7df588b004",
  "type": "FOOD",
  "amount": "999",
  "tax": "179",
  "totalAmount": "1178",
  "date": "Wed Dec 21 2022 18:03:26 GMT+0530 (India Standard Time)",
  "__v": 0
},{
  "_id": {
    "$oid": "63a2fdc3d7b6cc7df588b013"
  },
  "paymentPurpose": "Rojkharido Restaurant Registration",
  "planMonth": "1",
  "paymentStatus": "1",
  "paymentId": "pay_KuYvSJWdr4wWco",
  "storeId": "63a2fdc3d7b6cc7df588b011",
  "type": "FOOD",
  "amount": "999",
  "tax": "179",
  "totalAmount": "1178",
  "date": "Wed Dec 21 2022 18:06:19 GMT+0530 (India Standard Time)",
  "__v": 0
},{
  "_id": {
    "$oid": "63a2fe21d7b6cc7df588b020"
  },
  "paymentPurpose": "Rojkharido Restaurant Registration",
  "planMonth": "1",
  "paymentStatus": "1",
  "paymentId": "pay_KuYx5sPD9adOeA",
  "storeId": "63a2fe21d7b6cc7df588b01e",
  "type": "FOOD",
  "amount": "999",
  "tax": "179",
  "totalAmount": "1178",
  "date": "Wed Dec 21 2022 18:07:53 GMT+0530 (India Standard Time)",
  "__v": 0
},{
  "_id": {
    "$oid": "63a2fe7ad7b6cc7df588b02d"
  },
  "paymentPurpose": "Rojkharido Restaurant Registration",
  "planMonth": "1",
  "paymentStatus": "1",
  "paymentId": "pay_KuYyggyzeVfwji",
  "storeId": "63a2fe7ad7b6cc7df588b02b",
  "type": "FOOD",
  "amount": "999",
  "tax": "179",
  "totalAmount": "1178",
  "date": "Wed Dec 21 2022 18:09:22 GMT+0530 (India Standard Time)",
  "__v": 0
},{
  "_id": {
    "$oid": "63a2ff38d7b6cc7df588b03a"
  },
  "paymentPurpose": "Rojkharido Restaurant Registration",
  "planMonth": "1",
  "paymentStatus": "1",
  "paymentId": "pay_KuZ21eIBSgp0wM",
  "storeId": "63a2ff38d7b6cc7df588b038",
  "type": "FOOD",
  "amount": "999",
  "tax": "179",
  "totalAmount": "1178",
  "date": "Wed Dec 21 2022 18:12:32 GMT+0530 (India Standard Time)",
  "__v": 0
},{
  "_id": {
    "$oid": "63a2ffc0d7b6cc7df588b047"
  },
  "paymentPurpose": "Rojkharido Restaurant Registration",
  "planMonth": "1",
  "paymentStatus": "1",
  "paymentId": "pay_KuZ4PoN3qo97vV",
  "storeId": "63a2ffc0d7b6cc7df588b045",
  "type": "FOOD",
  "amount": "999",
  "tax": "179",
  "totalAmount": "1178",
  "date": "Wed Dec 21 2022 18:14:48 GMT+0530 (India Standard Time)",
  "__v": 0
},{
  "_id": {
    "$oid": "63a5afe898da47f27b1ee7a3"
  },
  "paymentPurpose": "Rojkharido Restaurant Registration",
  "planMonth": "1",
  "paymentStatus": "1",
  "paymentId": "pay_KvN5S2f55vQCRp",
  "storeId": "63a5afe898da47f27b1ee7a1",
  "type": "FOOD",
  "amount": "999",
  "tax": "179",
  "totalAmount": "1178",
  "date": "Fri Dec 23 2022 19:10:56 GMT+0530 (India Standard Time)",
  "__v": 0
},{
  "_id": {
    "$oid": "63a5b07398da47f27b1ee7b0"
  },
  "paymentPurpose": "Rojkharido Restaurant Registration",
  "planMonth": "1",
  "paymentStatus": "1",
  "paymentId": "pay_KvN8NZsfihjH44",
  "storeId": "63a5b07398da47f27b1ee7ae",
  "type": "FOOD",
  "amount": "999",
  "tax": "179",
  "totalAmount": "1178",
  "date": "Fri Dec 23 2022 19:13:15 GMT+0530 (India Standard Time)",
  "__v": 0
},{
  "_id": {
    "$oid": "63a5b0e198da47f27b1ee7bd"
  },
  "paymentPurpose": "Rojkharido Restaurant Registration",
  "planMonth": "1",
  "paymentStatus": "1",
  "paymentId": "pay_KvNAGFsxbjZtEk",
  "storeId": "63a5b0e198da47f27b1ee7bb",
  "type": "FOOD",
  "amount": "999",
  "tax": "179",
  "totalAmount": "1178",
  "date": "Fri Dec 23 2022 19:15:05 GMT+0530 (India Standard Time)",
  "__v": 0
},{
  "_id": {
    "$oid": "63a5b1ac98da47f27b1ee7ce"
  },
  "paymentPurpose": "Rojkharido Restaurant Registration",
  "planMonth": "1",
  "paymentStatus": "1",
  "paymentId": "pay_KvNDuhvd5pxP36",
  "storeId": "63a5b1ac98da47f27b1ee7cc",
  "type": "FOOD",
  "amount": "999",
  "tax": "179",
  "totalAmount": "1178",
  "date": "Fri Dec 23 2022 19:18:28 GMT+0530 (India Standard Time)",
  "__v": 0
},{
  "_id": {
    "$oid": "63a5b2f798da47f27b1ee7db"
  },
  "paymentPurpose": "Rojkharido Restaurant Registration",
  "planMonth": "1",
  "paymentStatus": "1",
  "paymentId": "pay_KvNJfKqf9CvNQp",
  "storeId": "63a5b2f798da47f27b1ee7d9",
  "type": "FOOD",
  "amount": "999",
  "tax": "179",
  "totalAmount": "1178",
  "date": "Fri Dec 23 2022 19:23:59 GMT+0530 (India Standard Time)",
  "__v": 0
},{
  "_id": {
    "$oid": "63a5b51198da47f27b1ee7e8"
  },
  "paymentPurpose": "Rojkharido Restaurant Registration",
  "planMonth": "1",
  "paymentStatus": "1",
  "paymentId": "pay_KvNTEEa2uEKq78",
  "storeId": "63a5b51198da47f27b1ee7e6",
  "type": "FOOD",
  "amount": "999",
  "tax": "179",
  "totalAmount": "1178",
  "date": "Fri Dec 23 2022 19:32:57 GMT+0530 (India Standard Time)",
  "__v": 0
},{
  "_id": {
    "$oid": "63a5b57e98da47f27b1ee7f5"
  },
  "paymentPurpose": "Rojkharido Restaurant Registration",
  "planMonth": "1",
  "paymentStatus": "1",
  "paymentId": "pay_KvNV9KhjYhjEjV",
  "storeId": "63a5b57e98da47f27b1ee7f3",
  "type": "FOOD",
  "amount": "999",
  "tax": "179",
  "totalAmount": "1178",
  "date": "Fri Dec 23 2022 19:34:46 GMT+0530 (India Standard Time)",
  "__v": 0
},{
  "_id": {
    "$oid": "63a5b62b98da47f27b1ee802"
  },
  "paymentPurpose": "Rojkharido Restaurant Registration",
  "planMonth": "1",
  "paymentStatus": "1",
  "paymentId": "pay_KvNYDAyoADlEdW",
  "storeId": "63a5b62b98da47f27b1ee800",
  "type": "FOOD",
  "amount": "999",
  "tax": "179",
  "totalAmount": "1178",
  "date": "Fri Dec 23 2022 19:37:39 GMT+0530 (India Standard Time)",
  "__v": 0
},{
  "_id": {
    "$oid": "63a5b69998da47f27b1ee80f"
  },
  "paymentPurpose": "Rojkharido Restaurant Registration",
  "planMonth": "1",
  "paymentStatus": "1",
  "paymentId": "pay_KvNa7HaQvFOiCT",
  "storeId": "63a5b69998da47f27b1ee80d",
  "type": "FOOD",
  "amount": "999",
  "tax": "179",
  "totalAmount": "1178",
  "date": "Fri Dec 23 2022 19:39:29 GMT+0530 (India Standard Time)",
  "__v": 0
},{
  "_id": {
    "$oid": "63b13edc2a870c24333e15da"
  },
  "paymentPurpose": "Rojkharido Restaurant Registration",
  "planMonth": "1",
  "paymentStatus": "1",
  "paymentId": "pay_KyqC1uDH30oJUS",
  "storeId": "63b13edc2a870c24333e15d8",
  "type": "FOOD",
  "amount": "999",
  "tax": "179",
  "totalAmount": "1178",
  "date": "Sun Jan 01 2023 13:35:48 GMT+0530 (India Standard Time)",
  "__v": 0
},{
  "_id": {
    "$oid": "63b13f5b2a870c24333e15e7"
  },
  "paymentPurpose": "Rojkharido Restaurant Registration",
  "planMonth": "1",
  "paymentStatus": "1",
  "paymentId": "pay_KyqE6JB0L0Q9b3",
  "storeId": "63b13f5b2a870c24333e15e5",
  "type": "FOOD",
  "amount": "999",
  "tax": "179",
  "totalAmount": "1178",
  "date": "Sun Jan 01 2023 13:37:55 GMT+0530 (India Standard Time)",
  "__v": 0
},{
  "_id": {
    "$oid": "63b13fc82a870c24333e15f4"
  },
  "paymentPurpose": "Rojkharido Restaurant Registration",
  "planMonth": "1",
  "paymentStatus": "1",
  "paymentId": "pay_KyqG9jXhjwxFL6",
  "storeId": "63b13fc82a870c24333e15f2",
  "type": "FOOD",
  "amount": "999",
  "tax": "179",
  "totalAmount": "1178",
  "date": "Sun Jan 01 2023 13:39:44 GMT+0530 (India Standard Time)",
  "__v": 0
},{
  "_id": {
    "$oid": "63b140302a870c24333e1601"
  },
  "paymentPurpose": "Rojkharido Restaurant Registration",
  "planMonth": "1",
  "paymentStatus": "1",
  "paymentId": "pay_KyqI1TCgykSW72",
  "storeId": "63b140302a870c24333e15ff",
  "type": "FOOD",
  "amount": "999",
  "tax": "179",
  "totalAmount": "1178",
  "date": "Sun Jan 01 2023 13:41:28 GMT+0530 (India Standard Time)",
  "__v": 0
},{
  "_id": {
    "$oid": "63b140a82a870c24333e160e"
  },
  "paymentPurpose": "Rojkharido Restaurant Registration",
  "planMonth": "1",
  "paymentStatus": "1",
  "paymentId": "pay_KyqK8iptR1E4CZ",
  "storeId": "63b140a82a870c24333e160c",
  "type": "FOOD",
  "amount": "999",
  "tax": "179",
  "totalAmount": "1178",
  "date": "Sun Jan 01 2023 13:43:28 GMT+0530 (India Standard Time)",
  "__v": 0
},{
  "_id": {
    "$oid": "63b1410f2a870c24333e161b"
  },
  "paymentPurpose": "Rojkharido Restaurant Registration",
  "planMonth": "1",
  "paymentStatus": "1",
  "paymentId": "pay_KyqLvLqPbegvX6",
  "storeId": "63b1410f2a870c24333e1619",
  "type": "FOOD",
  "amount": "999",
  "tax": "179",
  "totalAmount": "1178",
  "date": "Sun Jan 01 2023 13:45:11 GMT+0530 (India Standard Time)",
  "__v": 0
},{
  "_id": {
    "$oid": "63b141a42a870c24333e1628"
  },
  "paymentPurpose": "Rojkharido Restaurant Registration",
  "planMonth": "1",
  "paymentStatus": "1",
  "paymentId": "pay_KyqOZmXRlUYBiQ",
  "storeId": "63b141a42a870c24333e1626",
  "type": "FOOD",
  "amount": "999",
  "tax": "179",
  "totalAmount": "1178",
  "date": "Sun Jan 01 2023 13:47:40 GMT+0530 (India Standard Time)",
  "__v": 0
},{
  "_id": {
    "$oid": "63b142f12a870c24333e1635"
  },
  "paymentPurpose": "Rojkharido Restaurant Registration",
  "planMonth": "1",
  "paymentStatus": "1",
  "paymentId": "pay_KyqUQpEu5ZCAbF",
  "storeId": "63b142f12a870c24333e1633",
  "type": "FOOD",
  "amount": "999",
  "tax": "179",
  "totalAmount": "1178",
  "date": "Sun Jan 01 2023 13:53:13 GMT+0530 (India Standard Time)",
  "__v": 0
},{
  "_id": {
    "$oid": "63b143d22a870c24333e1642"
  },
  "paymentPurpose": "Rojkharido Restaurant Registration",
  "planMonth": "1",
  "paymentStatus": "1",
  "paymentId": "pay_KyqYN30Pp5SrC5",
  "storeId": "63b143d22a870c24333e1640",
  "type": "FOOD",
  "amount": "999",
  "tax": "179",
  "totalAmount": "1178",
  "date": "Sun Jan 01 2023 13:56:58 GMT+0530 (India Standard Time)",
  "__v": 0
},{
  "_id": {
    "$oid": "63b144802a870c24333e164f"
  },
  "paymentPurpose": "Rojkharido Restaurant Registration",
  "planMonth": "1",
  "paymentStatus": "1",
  "paymentId": "pay_KyqbSX1HNoBFWx",
  "storeId": "63b144802a870c24333e164d",
  "type": "FOOD",
  "amount": "999",
  "tax": "179",
  "totalAmount": "1178",
  "date": "Sun Jan 01 2023 13:59:52 GMT+0530 (India Standard Time)",
  "__v": 0
},{
  "_id": {
    "$oid": "63b145222a870c24333e165c"
  },
  "paymentPurpose": "Rojkharido Restaurant Registration",
  "planMonth": "1",
  "paymentStatus": "1",
  "paymentId": "pay_KyqeJiatHMPDhl",
  "storeId": "63b145222a870c24333e165a",
  "type": "FOOD",
  "amount": "999",
  "tax": "179",
  "totalAmount": "1178",
  "date": "Sun Jan 01 2023 14:02:34 GMT+0530 (India Standard Time)",
  "__v": 0
},{
  "_id": {
    "$oid": "63b1461b2a870c24333e1669"
  },
  "paymentPurpose": "Rojkharido Restaurant Registration",
  "planMonth": "1",
  "paymentStatus": "1",
  "paymentId": "pay_Kyqii05QTYTNno",
  "storeId": "63b1461b2a870c24333e1667",
  "type": "FOOD",
  "amount": "999",
  "tax": "179",
  "totalAmount": "1178",
  "date": "Sun Jan 01 2023 14:06:43 GMT+0530 (India Standard Time)",
  "__v": 0
},{
  "_id": {
    "$oid": "63b146942a870c24333e1676"
  },
  "paymentPurpose": "Rojkharido Restaurant Registration",
  "planMonth": "1",
  "paymentStatus": "1",
  "paymentId": "pay_Kyqkpyz2qmlLE8",
  "storeId": "63b146942a870c24333e1674",
  "type": "FOOD",
  "amount": "999",
  "tax": "179",
  "totalAmount": "1178",
  "date": "Sun Jan 01 2023 14:08:44 GMT+0530 (India Standard Time)",
  "__v": 0
},{
  "_id": {
    "$oid": "63b147412a870c24333e1683"
  },
  "paymentPurpose": "Rojkharido Restaurant Registration",
  "planMonth": "1",
  "paymentStatus": "1",
  "paymentId": "pay_KyqnsT4n8N8HdE",
  "storeId": "63b147412a870c24333e1681",
  "type": "FOOD",
  "amount": "999",
  "tax": "179",
  "totalAmount": "1178",
  "date": "Sun Jan 01 2023 14:11:37 GMT+0530 (India Standard Time)",
  "__v": 0
},{
  "_id": {
    "$oid": "63b148222a870c24333e1690"
  },
  "paymentPurpose": "Rojkharido Restaurant Registration",
  "planMonth": "1",
  "paymentStatus": "1",
  "paymentId": "pay_Kyqrov68gVqGn1",
  "storeId": "63b148222a870c24333e168e",
  "type": "FOOD",
  "amount": "999",
  "tax": "179",
  "totalAmount": "1178",
  "date": "Sun Jan 01 2023 14:15:22 GMT+0530 (India Standard Time)",
  "__v": 0
},{
  "_id": {
    "$oid": "63b1490b2a870c24333e169d"
  },
  "paymentPurpose": "Rojkharido Restaurant Registration",
  "planMonth": "1",
  "paymentStatus": "1",
  "paymentId": "pay_KyqvxcmjxKvoTe",
  "storeId": "63b1490b2a870c24333e169b",
  "type": "FOOD",
  "amount": "999",
  "tax": "179",
  "totalAmount": "1178",
  "date": "Sun Jan 01 2023 14:19:15 GMT+0530 (India Standard Time)",
  "__v": 0
},{
  "_id": {
    "$oid": "63b149bb2a870c24333e16aa"
  },
  "paymentPurpose": "Rojkharido Restaurant Registration",
  "planMonth": "1",
  "paymentStatus": "1",
  "paymentId": "pay_Kyqz2saSZss6Bl",
  "storeId": "63b149bb2a870c24333e16a8",
  "type": "FOOD",
  "amount": "999",
  "tax": "179",
  "totalAmount": "1178",
  "date": "Sun Jan 01 2023 14:22:11 GMT+0530 (India Standard Time)",
  "__v": 0
},{
  "_id": {
    "$oid": "63b14c152a870c24333e16b7"
  },
  "paymentPurpose": "Rojkharido Restaurant Registration",
  "planMonth": "1",
  "paymentStatus": "1",
  "paymentId": "pay_Kyr9enUG3DcGqh",
  "storeId": "63b14c152a870c24333e16b5",
  "type": "FOOD",
  "amount": "999",
  "tax": "179",
  "totalAmount": "1178",
  "date": "Sun Jan 01 2023 14:32:13 GMT+0530 (India Standard Time)",
  "__v": 0
},{
  "_id": {
    "$oid": "63b14cd12a870c24333e16c4"
  },
  "paymentPurpose": "Rojkharido Restaurant Registration",
  "planMonth": "1",
  "paymentStatus": "1",
  "paymentId": "pay_KyrCyDNFlvCvDS",
  "storeId": "63b14cd12a870c24333e16c2",
  "type": "FOOD",
  "amount": "999",
  "tax": "179",
  "totalAmount": "1178",
  "date": "Sun Jan 01 2023 14:35:21 GMT+0530 (India Standard Time)",
  "__v": 0
},{
  "_id": {
    "$oid": "63b14d462a870c24333e16d1"
  },
  "paymentPurpose": "Rojkharido Restaurant Registration",
  "planMonth": "1",
  "paymentStatus": "1",
  "paymentId": "pay_KyrF0rfV00sNJV",
  "storeId": "63b14d462a870c24333e16cf",
  "type": "FOOD",
  "amount": "999",
  "tax": "179",
  "totalAmount": "1178",
  "date": "Sun Jan 01 2023 14:37:18 GMT+0530 (India Standard Time)",
  "__v": 0
},{
  "_id": {
    "$oid": "63b14db12a870c24333e16e6"
  },
  "paymentPurpose": "Rojkharido Restaurant Registration",
  "planMonth": "1",
  "paymentStatus": "1",
  "paymentId": "pay_KyrGuISZnKL5ED",
  "storeId": "63b14db12a870c24333e16e4",
  "type": "FOOD",
  "amount": "999",
  "tax": "179",
  "totalAmount": "1178",
  "date": "Sun Jan 01 2023 14:39:05 GMT+0530 (India Standard Time)",
  "__v": 0
},{
  "_id": {
    "$oid": "63b150702a870c24333e16f3"
  },
  "paymentPurpose": "Rojkharido Restaurant Registration",
  "planMonth": "1",
  "paymentStatus": "1",
  "paymentId": "pay_KyrTH5FeKFkYll",
  "storeId": "63b150702a870c24333e16f1",
  "type": "FOOD",
  "amount": "999",
  "tax": "179",
  "totalAmount": "1178",
  "date": "Sun Jan 01 2023 14:50:48 GMT+0530 (India Standard Time)",
  "__v": 0
},{
  "_id": {
    "$oid": "63ba778cbdc1d96fce126d62"
  },
  "paymentPurpose": "Rojkharido Restaurant Registration",
  "planMonth": "1",
  "paymentStatus": "1",
  "paymentId": "pay_L1bniTxkaiu1MR",
  "storeId": "63ba778cbdc1d96fce126d60",
  "type": "FOOD",
  "amount": "999",
  "tax": "179",
  "totalAmount": "1178",
  "date": "Sun Jan 08 2023 13:28:04 GMT+0530 (India Standard Time)",
  "__v": 0
}]